<?xml version="1.0" encoding="utf-8"?>
<hero_skill_set guid="946127391" id="WP_Item_DA" revision="0" description="아이템 단검 스킬" feature_tag="BASE_LH" publisher_tag="ALL" defense_complex_guid="0" _fsg_copyable="true" _fsg_movable="true">
  <skill_complex_list>
    <skill_complex guid="945537567" is_basic_attack="false" is_for_polymorphed_only="false" description="광란의 난도질" unlock_level="1" id="SkillSet_WP_Item_Boss_T2_DA_01" skill_enchant_category="kNone" skill_type="kPassiveSkill" feature_tag="BASE_LH" publisher_tag="ALL" skill_slot_affinity="kNotAssigned">
      <context uid="0" feature_tag="BASE_LH" publisher_tag="ALL" unlock_level="1" min_skill_level="1" max_skill_level="1">
        <presets>
          <preset guid="945472031" is_toggle_slot="false">
            <default uid="0">
              <combo_state_default>
                <simple skill_id="WP_Item_Boss_T2_DA_01" skill_id_disable="false" />
                <transition>
                  <use_skill skill_id="WP_Item_Boss_T2_DA_01" next_combo_state="kComboStateDefault" />
                </transition>
              </combo_state_default>
            </default>
          </preset>
        </presets>
      </context>
      <context uid="1" feature_tag="BASE_LH" publisher_tag="ALL" min_skill_level="2" max_skill_level="2">
        <presets>
          <preset guid="945406495" is_toggle_slot="false">
            <default uid="0">
              <combo_state_default>
                <simple skill_id="WP_Item_Boss_T2_DA_01" skill_id_disable="false" />
                <transition>
                  <use_skill skill_id="WP_Item_Boss_T2_DA_01" next_combo_state="kComboStateDefault" />
                </transition>
              </combo_state_default>
            </default>
          </preset>
        </presets>
      </context>
      <context uid="2" feature_tag="BASE_LH" publisher_tag="ALL" min_skill_level="3" max_skill_level="3">
        <presets>
          <preset guid="945340959" is_toggle_slot="false">
            <default uid="0">
              <combo_state_default>
                <simple skill_id="WP_Item_Boss_T2_DA_01" skill_id_disable="false" />
                <transition>
                  <use_skill skill_id="WP_Item_Boss_T2_DA_01" next_combo_state="kComboStateDefault" />
                </transition>
              </combo_state_default>
            </default>
          </preset>
        </presets>
      </context>
      <context uid="3" feature_tag="BASE_LH" publisher_tag="ALL" min_skill_level="4" max_skill_level="4">
        <presets>
          <preset guid="945799711" is_toggle_slot="false">
            <default uid="0">
              <combo_state_default>
                <simple skill_id="WP_Item_Boss_T2_DA_01" skill_id_disable="false" />
                <transition>
                  <use_skill skill_id="WP_Item_Boss_T2_DA_01" next_combo_state="kComboStateDefault" />
                </transition>
              </combo_state_default>
            </default>
          </preset>
        </presets>
      </context>
      <context uid="4" feature_tag="BASE_LH" publisher_tag="ALL" min_skill_level="5" max_skill_level="5">
        <presets>
          <preset guid="945734175" is_toggle_slot="false">
            <default uid="0">
              <combo_state_default>
                <simple skill_id="WP_Item_Boss_T2_DA_01" skill_id_disable="false" />
                <transition>
                  <use_skill skill_id="WP_Item_Boss_T2_DA_01" next_combo_state="kComboStateDefault" />
                </transition>
              </combo_state_default>
            </default>
          </preset>
        </presets>
      </context>
      <context uid="5" feature_tag="BASE_LH" publisher_tag="ALL" min_skill_level="6" max_skill_level="6">
        <presets>
          <preset guid="945668639" is_toggle_slot="false">
            <default uid="0">
              <combo_state_default>
                <simple skill_id="WP_Item_Boss_T2_DA_01" skill_id_disable="false" />
                <transition>
                  <use_skill skill_id="WP_Item_Boss_T2_DA_01" next_combo_state="kComboStateDefault" />
                </transition>
              </combo_state_default>
            </default>
          </preset>
        </presets>
      </context>
      <context uid="6" feature_tag="BASE_LH" publisher_tag="ALL" min_skill_level="7" max_skill_level="7">
        <presets>
          <preset guid="945603103" is_toggle_slot="false">
            <default uid="0">
              <combo_state_default>
                <simple skill_id="WP_Item_Boss_T2_DA_01" skill_id_disable="false" />
                <transition>
                  <use_skill skill_id="WP_Item_Boss_T2_DA_01" next_combo_state="kComboStateDefault" />
                </transition>
              </combo_state_default>
            </default>
          </preset>
        </presets>
      </context>
      <context uid="7" feature_tag="BASE_LH" publisher_tag="ALL" min_skill_level="8" max_skill_level="8">
        <presets>
          <preset guid="945013279" is_toggle_slot="false">
            <default uid="0">
              <combo_state_default>
                <simple skill_id="WP_Item_Boss_T2_DA_01" skill_id_disable="false" />
                <transition>
                  <use_skill skill_id="WP_Item_Boss_T2_DA_01" next_combo_state="kComboStateDefault" />
                </transition>
              </combo_state_default>
            </default>
          </preset>
        </presets>
      </context>
      <context uid="8" feature_tag="BASE_LH" publisher_tag="ALL" min_skill_level="9" max_skill_level="9">
        <presets>
          <preset guid="944947743" is_toggle_slot="false">
            <default uid="0">
              <combo_state_default>
                <simple skill_id="WP_Item_Boss_T2_DA_01" skill_id_disable="false" />
                <transition>
                  <use_skill skill_id="WP_Item_Boss_T2_DA_01" next_combo_state="kComboStateDefault" />
                </transition>
              </combo_state_default>
            </default>
          </preset>
        </presets>
      </context>
      <context uid="9" feature_tag="BASE_LH" publisher_tag="ALL" min_skill_level="10" max_skill_level="10">
        <presets>
          <preset guid="944882207" is_toggle_slot="false">
            <default uid="0">
              <combo_state_default>
                <simple skill_id="WP_Item_Boss_T2_DA_01" skill_id_disable="false" />
                <transition>
                  <use_skill skill_id="WP_Item_Boss_T2_DA_01" next_combo_state="kComboStateDefault" />
                </transition>
              </combo_state_default>
            </default>
          </preset>
        </presets>
      </context>
      <context uid="10" feature_tag="BASE_LH" publisher_tag="ALL" min_skill_level="11" max_skill_level="11">
        <presets>
          <preset guid="944816671" is_toggle_slot="false">
            <default uid="0">
              <combo_state_default>
                <simple skill_id="WP_Item_Boss_T2_DA_01" skill_id_disable="false" />
                <transition>
                  <use_skill skill_id="WP_Item_Boss_T2_DA_01" next_combo_state="kComboStateDefault" />
                </transition>
              </combo_state_default>
            </default>
          </preset>
        </presets>
      </context>
      <context uid="11" feature_tag="BASE_LH" publisher_tag="ALL" min_skill_level="12" max_skill_level="12">
        <presets>
          <preset guid="945275423" is_toggle_slot="false">
            <default uid="0">
              <combo_state_default>
                <simple skill_id="WP_Item_Boss_T2_DA_01" skill_id_disable="false" />
                <transition>
                  <use_skill skill_id="WP_Item_Boss_T2_DA_01" next_combo_state="kComboStateDefault" />
                </transition>
              </combo_state_default>
            </default>
          </preset>
        </presets>
      </context>
      <context uid="12" feature_tag="BASE_LH" publisher_tag="ALL" min_skill_level="13" max_skill_level="13">
        <presets>
          <preset guid="945209887" is_toggle_slot="false">
            <default uid="0">
              <combo_state_default>
                <simple skill_id="WP_Item_Boss_T2_DA_01" skill_id_disable="false" />
                <transition>
                  <use_skill skill_id="WP_Item_Boss_T2_DA_01" next_combo_state="kComboStateDefault" />
                </transition>
              </combo_state_default>
            </default>
          </preset>
        </presets>
      </context>
      <context uid="13" feature_tag="BASE_LH" publisher_tag="ALL" min_skill_level="14" max_skill_level="14">
        <presets>
          <preset guid="945144351" is_toggle_slot="false">
            <default uid="0">
              <combo_state_default>
                <simple skill_id="WP_Item_Boss_T2_DA_01" skill_id_disable="false" />
                <transition>
                  <use_skill skill_id="WP_Item_Boss_T2_DA_01" next_combo_state="kComboStateDefault" />
                </transition>
              </combo_state_default>
            </default>
          </preset>
        </presets>
      </context>
      <context uid="14" feature_tag="BASE_LH" publisher_tag="ALL" min_skill_level="15" max_skill_level="15">
        <presets>
          <preset guid="945078815" is_toggle_slot="false">
            <default uid="0">
              <combo_state_default>
                <simple skill_id="WP_Item_Boss_T2_DA_01" skill_id_disable="false" />
                <transition>
                  <use_skill skill_id="WP_Item_Boss_T2_DA_01" next_combo_state="kComboStateDefault" />
                </transition>
              </combo_state_default>
            </default>
          </preset>
        </presets>
      </context>
      <context uid="15" feature_tag="BASE_LH" publisher_tag="ALL" min_skill_level="16" max_skill_level="16">
        <presets>
          <preset guid="944488991" is_toggle_slot="false">
            <default uid="0">
              <combo_state_default>
                <simple skill_id="WP_Item_Boss_T2_DA_01" skill_id_disable="false" />
                <transition>
                  <use_skill skill_id="WP_Item_Boss_T2_DA_01" next_combo_state="kComboStateDefault" />
                </transition>
              </combo_state_default>
            </default>
          </preset>
        </presets>
      </context>
      <context uid="16" feature_tag="BASE_LH" publisher_tag="ALL" min_skill_level="17" max_skill_level="17">
        <presets>
          <preset guid="944423455" is_toggle_slot="false">
            <default uid="0">
              <combo_state_default>
                <simple skill_id="WP_Item_Boss_T2_DA_01" skill_id_disable="false" />
                <transition>
                  <use_skill skill_id="WP_Item_Boss_T2_DA_01" next_combo_state="kComboStateDefault" />
                </transition>
              </combo_state_default>
            </default>
          </preset>
        </presets>
      </context>
      <context uid="17" feature_tag="BASE_LH" publisher_tag="ALL" min_skill_level="18" max_skill_level="18">
        <presets>
          <preset guid="944357919" is_toggle_slot="false">
            <default uid="0">
              <combo_state_default>
                <simple skill_id="WP_Item_Boss_T2_DA_01" skill_id_disable="false" />
                <transition>
                  <use_skill skill_id="WP_Item_Boss_T2_DA_01" next_combo_state="kComboStateDefault" />
                </transition>
              </combo_state_default>
            </default>
          </preset>
        </presets>
      </context>
      <context uid="18" feature_tag="BASE_LH" publisher_tag="ALL" min_skill_level="19" max_skill_level="19">
        <presets>
          <preset guid="944292383" is_toggle_slot="false">
            <default uid="0">
              <combo_state_default>
                <simple skill_id="WP_Item_Boss_T2_DA_01" skill_id_disable="false" />
                <transition>
                  <use_skill skill_id="WP_Item_Boss_T2_DA_01" next_combo_state="kComboStateDefault" />
                </transition>
              </combo_state_default>
            </default>
          </preset>
        </presets>
      </context>
      <context uid="19" feature_tag="BASE_LH" publisher_tag="ALL" min_skill_level="20" max_skill_level="20">
        <presets>
          <preset guid="944751135" is_toggle_slot="false">
            <default uid="0">
              <combo_state_default>
                <simple skill_id="WP_Item_Boss_T2_DA_01" skill_id_disable="false" />
                <transition>
                  <use_skill skill_id="WP_Item_Boss_T2_DA_01" next_combo_state="kComboStateDefault" />
                </transition>
              </combo_state_default>
            </default>
          </preset>
        </presets>
      </context>
      <trait_list />
    </skill_complex>
    <skill_complex guid="944620065" is_basic_attack="false" is_for_polymorphed_only="false" description="고요의 추적자" unlock_level="1" id="SkillSet_WP_Item_Boss_T2_DA_02" skill_enchant_category="kNone" skill_type="kPassiveSkill" feature_tag="BASE_LH" publisher_tag="ALL" skill_slot_affinity="kNotAssigned">
      <context uid="0" feature_tag="BASE_LH" publisher_tag="ALL" unlock_level="1" min_skill_level="1" max_skill_level="1">
        <presets>
          <preset guid="944554529" is_toggle_slot="false">
            <default uid="0">
              <combo_state_default>
                <simple skill_id="WP_Item_Boss_T2_DA_02" skill_id_disable="false" />
                <transition>
                  <use_skill skill_id="WP_Item_Boss_T2_DA_02" next_combo_state="kComboStateDefault" />
                </transition>
              </combo_state_default>
            </default>
          </preset>
        </presets>
      </context>
      <context uid="1" feature_tag="BASE_LH" publisher_tag="ALL" min_skill_level="2" max_skill_level="2">
        <presets>
          <preset guid="943964705" is_toggle_slot="false">
            <default uid="0">
              <combo_state_default>
                <simple skill_id="WP_Item_Boss_T2_DA_02" skill_id_disable="false" />
                <transition>
                  <use_skill skill_id="WP_Item_Boss_T2_DA_02" next_combo_state="kComboStateDefault" />
                </transition>
              </combo_state_default>
            </default>
          </preset>
        </presets>
      </context>
      <context uid="2" feature_tag="BASE_LH" publisher_tag="ALL" min_skill_level="3" max_skill_level="3">
        <presets>
          <preset guid="943899169" is_toggle_slot="false">
            <default uid="0">
              <combo_state_default>
                <simple skill_id="WP_Item_Boss_T2_DA_02" skill_id_disable="false" />
                <transition>
                  <use_skill skill_id="WP_Item_Boss_T2_DA_02" next_combo_state="kComboStateDefault" />
                </transition>
              </combo_state_default>
            </default>
          </preset>
        </presets>
      </context>
      <context uid="3" feature_tag="BASE_LH" publisher_tag="ALL" min_skill_level="4" max_skill_level="4">
        <presets>
          <preset guid="943833633" is_toggle_slot="false">
            <default uid="0">
              <combo_state_default>
                <simple skill_id="WP_Item_Boss_T2_DA_02" skill_id_disable="false" />
                <transition>
                  <use_skill skill_id="WP_Item_Boss_T2_DA_02" next_combo_state="kComboStateDefault" />
                </transition>
              </combo_state_default>
            </default>
          </preset>
        </presets>
      </context>
      <context uid="4" feature_tag="BASE_LH" publisher_tag="ALL" min_skill_level="5" max_skill_level="5">
        <presets>
          <preset guid="943768097" is_toggle_slot="false">
            <default uid="0">
              <combo_state_default>
                <simple skill_id="WP_Item_Boss_T2_DA_02" skill_id_disable="false" />
                <transition>
                  <use_skill skill_id="WP_Item_Boss_T2_DA_02" next_combo_state="kComboStateDefault" />
                </transition>
              </combo_state_default>
            </default>
          </preset>
        </presets>
      </context>
      <context uid="5" feature_tag="BASE_LH" publisher_tag="ALL" min_skill_level="6" max_skill_level="6">
        <presets>
          <preset guid="944226849" is_toggle_slot="false">
            <default uid="0">
              <combo_state_default>
                <simple skill_id="WP_Item_Boss_T2_DA_02" skill_id_disable="false" />
                <transition>
                  <use_skill skill_id="WP_Item_Boss_T2_DA_02" next_combo_state="kComboStateDefault" />
                </transition>
              </combo_state_default>
            </default>
          </preset>
        </presets>
      </context>
      <context uid="6" feature_tag="BASE_LH" publisher_tag="ALL" min_skill_level="7" max_skill_level="7">
        <presets>
          <preset guid="944161313" is_toggle_slot="false">
            <default uid="0">
              <combo_state_default>
                <simple skill_id="WP_Item_Boss_T2_DA_02" skill_id_disable="false" />
                <transition>
                  <use_skill skill_id="WP_Item_Boss_T2_DA_02" next_combo_state="kComboStateDefault" />
                </transition>
              </combo_state_default>
            </default>
          </preset>
        </presets>
      </context>
      <context uid="7" feature_tag="BASE_LH" publisher_tag="ALL" min_skill_level="8" max_skill_level="8">
        <presets>
          <preset guid="944095777" is_toggle_slot="false">
            <default uid="0">
              <combo_state_default>
                <simple skill_id="WP_Item_Boss_T2_DA_02" skill_id_disable="false" />
                <transition>
                  <use_skill skill_id="WP_Item_Boss_T2_DA_02" next_combo_state="kComboStateDefault" />
                </transition>
              </combo_state_default>
            </default>
          </preset>
        </presets>
      </context>
      <context uid="8" feature_tag="BASE_LH" publisher_tag="ALL" min_skill_level="9" max_skill_level="9">
        <presets>
          <preset guid="944030241" is_toggle_slot="false">
            <default uid="0">
              <combo_state_default>
                <simple skill_id="WP_Item_Boss_T2_DA_02" skill_id_disable="false" />
                <transition>
                  <use_skill skill_id="WP_Item_Boss_T2_DA_02" next_combo_state="kComboStateDefault" />
                </transition>
              </combo_state_default>
            </default>
          </preset>
        </presets>
      </context>
      <context uid="9" feature_tag="BASE_LH" publisher_tag="ALL" min_skill_level="10" max_skill_level="10">
        <presets>
          <preset guid="943440417" is_toggle_slot="false">
            <default uid="0">
              <combo_state_default>
                <simple skill_id="WP_Item_Boss_T2_DA_02" skill_id_disable="false" />
                <transition>
                  <use_skill skill_id="WP_Item_Boss_T2_DA_02" next_combo_state="kComboStateDefault" />
                </transition>
              </combo_state_default>
            </default>
          </preset>
        </presets>
      </context>
      <context uid="10" feature_tag="BASE_LH" publisher_tag="ALL" min_skill_level="11" max_skill_level="11">
        <presets>
          <preset guid="943374881" is_toggle_slot="false">
            <default uid="0">
              <combo_state_default>
                <simple skill_id="WP_Item_Boss_T2_DA_02" skill_id_disable="false" />
                <transition>
                  <use_skill skill_id="WP_Item_Boss_T2_DA_02" next_combo_state="kComboStateDefault" />
                </transition>
              </combo_state_default>
            </default>
          </preset>
        </presets>
      </context>
      <context uid="11" feature_tag="BASE_LH" publisher_tag="ALL" min_skill_level="12" max_skill_level="12">
        <presets>
          <preset guid="943309345" is_toggle_slot="false">
            <default uid="0">
              <combo_state_default>
                <simple skill_id="WP_Item_Boss_T2_DA_02" skill_id_disable="false" />
                <transition>
                  <use_skill skill_id="WP_Item_Boss_T2_DA_02" next_combo_state="kComboStateDefault" />
                </transition>
              </combo_state_default>
            </default>
          </preset>
        </presets>
      </context>
      <context uid="12" feature_tag="BASE_LH" publisher_tag="ALL" min_skill_level="13" max_skill_level="13">
        <presets>
          <preset guid="943243809" is_toggle_slot="false">
            <default uid="0">
              <combo_state_default>
                <simple skill_id="WP_Item_Boss_T2_DA_02" skill_id_disable="false" />
                <transition>
                  <use_skill skill_id="WP_Item_Boss_T2_DA_02" next_combo_state="kComboStateDefault" />
                </transition>
              </combo_state_default>
            </default>
          </preset>
        </presets>
      </context>
      <context uid="13" feature_tag="BASE_LH" publisher_tag="ALL" min_skill_level="14" max_skill_level="14">
        <presets>
          <preset guid="943702561" is_toggle_slot="false">
            <default uid="0">
              <combo_state_default>
                <simple skill_id="WP_Item_Boss_T2_DA_02" skill_id_disable="false" />
                <transition>
                  <use_skill skill_id="WP_Item_Boss_T2_DA_02" next_combo_state="kComboStateDefault" />
                </transition>
              </combo_state_default>
            </default>
          </preset>
        </presets>
      </context>
      <context uid="14" feature_tag="BASE_LH" publisher_tag="ALL" min_skill_level="15" max_skill_level="15">
        <presets>
          <preset guid="943637025" is_toggle_slot="false">
            <default uid="0">
              <combo_state_default>
                <simple skill_id="WP_Item_Boss_T2_DA_02" skill_id_disable="false" />
                <transition>
                  <use_skill skill_id="WP_Item_Boss_T2_DA_02" next_combo_state="kComboStateDefault" />
                </transition>
              </combo_state_default>
            </default>
          </preset>
        </presets>
      </context>
      <context uid="15" feature_tag="BASE_LH" publisher_tag="ALL" min_skill_level="16" max_skill_level="16">
        <presets>
          <preset guid="943571489" is_toggle_slot="false">
            <default uid="0">
              <combo_state_default>
                <simple skill_id="WP_Item_Boss_T2_DA_02" skill_id_disable="false" />
                <transition>
                  <use_skill skill_id="WP_Item_Boss_T2_DA_02" next_combo_state="kComboStateDefault" />
                </transition>
              </combo_state_default>
            </default>
          </preset>
        </presets>
      </context>
      <context uid="16" feature_tag="BASE_LH" publisher_tag="ALL" min_skill_level="17" max_skill_level="17">
        <presets>
          <preset guid="943505953" is_toggle_slot="false">
            <default uid="0">
              <combo_state_default>
                <simple skill_id="WP_Item_Boss_T2_DA_02" skill_id_disable="false" />
                <transition>
                  <use_skill skill_id="WP_Item_Boss_T2_DA_02" next_combo_state="kComboStateDefault" />
                </transition>
              </combo_state_default>
            </default>
          </preset>
        </presets>
      </context>
      <context uid="17" feature_tag="BASE_LH" publisher_tag="ALL" min_skill_level="18" max_skill_level="18">
        <presets>
          <preset guid="942916129" is_toggle_slot="false">
            <default uid="0">
              <combo_state_default>
                <simple skill_id="WP_Item_Boss_T2_DA_02" skill_id_disable="false" />
                <transition>
                  <use_skill skill_id="WP_Item_Boss_T2_DA_02" next_combo_state="kComboStateDefault" />
                </transition>
              </combo_state_default>
            </default>
          </preset>
        </presets>
      </context>
      <context uid="18" feature_tag="BASE_LH" publisher_tag="ALL" min_skill_level="19" max_skill_level="19">
        <presets>
          <preset guid="942850593" is_toggle_slot="false">
            <default uid="0">
              <combo_state_default>
                <simple skill_id="WP_Item_Boss_T2_DA_02" skill_id_disable="false" />
                <transition>
                  <use_skill skill_id="WP_Item_Boss_T2_DA_02" next_combo_state="kComboStateDefault" />
                </transition>
              </combo_state_default>
            </default>
          </preset>
        </presets>
      </context>
      <context uid="19" feature_tag="BASE_LH" publisher_tag="ALL" min_skill_level="20" max_skill_level="20">
        <presets>
          <preset guid="942785057" is_toggle_slot="false">
            <default uid="0">
              <combo_state_default>
                <simple skill_id="WP_Item_Boss_T2_DA_02" skill_id_disable="false" />
                <transition>
                  <use_skill skill_id="WP_Item_Boss_T2_DA_02" next_combo_state="kComboStateDefault" />
                </transition>
              </combo_state_default>
            </default>
          </preset>
        </presets>
      </context>
      <trait_list />
    </skill_complex>
    <skill_complex guid="944489441" is_basic_attack="false" is_for_polymorphed_only="false" description="레비아탄의 악령손" unlock_level="1" id="SkillSet_WP_Item_Boss_T2_DA_03" skill_enchant_category="kNone" skill_type="kPassiveSkill" feature_tag="BASE_LH" publisher_tag="ALL" skill_slot_affinity="kNotAssigned">
      <context uid="0" feature_tag="BASE_LH" publisher_tag="ALL" unlock_level="1" min_skill_level="1" max_skill_level="1">
        <presets>
          <preset guid="944423905" is_toggle_slot="false">
            <default uid="0">
              <combo_state_default>
                <simple skill_id="WP_Item_Boss_T2_DA_03" skill_id_disable="false" />
                <transition>
                  <use_skill skill_id="WP_Item_Boss_T2_DA_03" next_combo_state="kComboStateDefault" />
                </transition>
              </combo_state_default>
            </default>
          </preset>
        </presets>
      </context>
      <trait_list />
    </skill_complex>
    <skill_complex guid="945931235" is_basic_attack="false" is_for_polymorphed_only="false" description="베르칸트의 매혹날" unlock_level="1" id="SkillSet_WP_Item_Boss_T2_DA_04" skill_enchant_category="kNone" skill_type="kPassiveSkill" feature_tag="BASE_LH" publisher_tag="ALL" skill_slot_affinity="kNotAssigned">
      <context uid="0" feature_tag="BASE_LH" publisher_tag="ALL" unlock_level="1" min_skill_level="1" max_skill_level="1">
        <presets>
          <preset guid="945865699" is_toggle_slot="false">
            <default uid="0">
              <combo_state_default>
                <simple skill_id="WP_Item_Boss_T2_DA_04" skill_id_disable="false" />
                <transition>
                  <use_skill skill_id="WP_Item_Boss_T2_DA_04" next_combo_state="kComboStateDefault" />
                </transition>
              </combo_state_default>
            </default>
          </preset>
        </presets>
      </context>
      <trait_list />
    </skill_complex>
    <skill_complex guid="949055245" is_basic_attack="false" is_for_polymorphed_only="false" description="레퀴루스의 가시날" unlock_level="1" id="SkillSet_WP_Item_kA_DA_57" skill_enchant_category="kNone" skill_type="kPassiveSkill" feature_tag="BASE_LH" publisher_tag="ALL" skill_slot_affinity="kNotAssigned">
      <context uid="0" unlock_level="1" feature_tag="BASE_LH" publisher_tag="ALL" min_skill_level="1" max_skill_level="1">
        <presets>
          <preset guid="949120781" is_toggle_slot="false">
            <default uid="0">
              <combo_state_default>
                <simple skill_id="WP_Item_kA_DA_57" skill_id_disable="false" />
                <transition>
                  <use_skill skill_id="WP_Item_kA_DA_57" next_combo_state="kComboStateDefault" />
                </transition>
              </combo_state_default>
            </default>
          </preset>
        </presets>
      </context>
      <context uid="1" feature_tag="BASE_LH" publisher_tag="ALL" min_skill_level="2" max_skill_level="2">
        <presets>
          <preset guid="950876051" is_toggle_slot="false">
            <default uid="0">
              <combo_state_default>
                <simple skill_id="WP_Item_kA_DA_57" skill_id_disable="false" />
                <transition>
                  <use_skill skill_id="WP_Item_kA_DA_57" next_combo_state="kComboStateDefault" />
                </transition>
              </combo_state_default>
            </default>
          </preset>
        </presets>
      </context>
      <context uid="2" feature_tag="BASE_LH" publisher_tag="ALL" min_skill_level="3" max_skill_level="3">
        <presets>
          <preset guid="950941594" is_toggle_slot="false">
            <default uid="0">
              <combo_state_default>
                <simple skill_id="WP_Item_kA_DA_57" skill_id_disable="false" />
                <transition>
                  <use_skill skill_id="WP_Item_kA_DA_57" next_combo_state="kComboStateDefault" />
                </transition>
              </combo_state_default>
            </default>
          </preset>
        </presets>
      </context>
      <context uid="3" feature_tag="BASE_LH" publisher_tag="ALL" min_skill_level="4" max_skill_level="4">
        <presets>
          <preset guid="951007134" is_toggle_slot="false">
            <default uid="0">
              <combo_state_default>
                <simple skill_id="WP_Item_kA_DA_57" skill_id_disable="false" />
                <transition>
                  <use_skill skill_id="WP_Item_kA_DA_57" next_combo_state="kComboStateDefault" />
                </transition>
              </combo_state_default>
            </default>
          </preset>
        </presets>
      </context>
      <context uid="4" feature_tag="BASE_LH" publisher_tag="ALL" min_skill_level="5" max_skill_level="5">
        <presets>
          <preset guid="950548383" is_toggle_slot="false">
            <default uid="0">
              <combo_state_default>
                <simple skill_id="WP_Item_kA_DA_57" skill_id_disable="false" />
                <transition>
                  <use_skill skill_id="WP_Item_kA_DA_57" next_combo_state="kComboStateDefault" />
                </transition>
              </combo_state_default>
            </default>
          </preset>
        </presets>
      </context>
      <context uid="5" feature_tag="BASE_LH" publisher_tag="ALL" min_skill_level="6" max_skill_level="6">
        <presets>
          <preset guid="954374766" is_toggle_slot="false">
            <default uid="0">
              <combo_state_default>
                <simple skill_id="WP_Item_kA_DA_57" skill_id_disable="false" />
                <transition>
                  <use_skill skill_id="WP_Item_kA_DA_57" next_combo_state="kComboStateDefault" />
                </transition>
              </combo_state_default>
            </default>
          </preset>
        </presets>
      </context>
      <context uid="6" feature_tag="BASE_LH" publisher_tag="ALL" min_skill_level="7" max_skill_level="7">
        <presets>
          <preset guid="954440303" is_toggle_slot="false">
            <default uid="0">
              <combo_state_default>
                <simple skill_id="WP_Item_kA_DA_57" skill_id_disable="false" />
                <transition>
                  <use_skill skill_id="WP_Item_kA_DA_57" next_combo_state="kComboStateDefault" />
                </transition>
              </combo_state_default>
            </default>
          </preset>
        </presets>
      </context>
      <context uid="7" feature_tag="BASE_LH" publisher_tag="ALL" min_skill_level="8" max_skill_level="8">
        <presets>
          <preset guid="954243696" is_toggle_slot="false">
            <default uid="0">
              <combo_state_default>
                <simple skill_id="WP_Item_kA_DA_57" skill_id_disable="false" />
                <transition>
                  <use_skill skill_id="WP_Item_kA_DA_57" next_combo_state="kComboStateDefault" />
                </transition>
              </combo_state_default>
            </default>
          </preset>
        </presets>
      </context>
      <context uid="8" feature_tag="BASE_LH" publisher_tag="ALL" min_skill_level="9" max_skill_level="9">
        <presets>
          <preset guid="954309233" is_toggle_slot="false">
            <default uid="0">
              <combo_state_default>
                <simple skill_id="WP_Item_kA_DA_57" skill_id_disable="false" />
                <transition>
                  <use_skill skill_id="WP_Item_kA_DA_57" next_combo_state="kComboStateDefault" />
                </transition>
              </combo_state_default>
            </default>
          </preset>
        </presets>
      </context>
      <context uid="9" feature_tag="BASE_LH" publisher_tag="ALL" min_skill_level="10" max_skill_level="10">
        <presets>
          <preset guid="954636914" is_toggle_slot="false">
            <default uid="0">
              <combo_state_default>
                <simple skill_id="WP_Item_kA_DA_57" skill_id_disable="false" />
                <transition>
                  <use_skill skill_id="WP_Item_kA_DA_57" next_combo_state="kComboStateDefault" />
                </transition>
              </combo_state_default>
            </default>
          </preset>
        </presets>
      </context>
      <context uid="10" feature_tag="BASE_LH" publisher_tag="ALL" min_skill_level="11" max_skill_level="11">
        <presets>
          <preset guid="954702451" is_toggle_slot="false">
            <default uid="0">
              <combo_state_default>
                <simple skill_id="WP_Item_kA_DA_57" skill_id_disable="false" />
                <transition>
                  <use_skill skill_id="WP_Item_kA_DA_57" next_combo_state="kComboStateDefault" />
                </transition>
              </combo_state_default>
            </default>
          </preset>
        </presets>
      </context>
      <context uid="11" feature_tag="BASE_LH" publisher_tag="ALL" min_skill_level="12" max_skill_level="12">
        <presets>
          <preset guid="954505844" is_toggle_slot="false">
            <default uid="0">
              <combo_state_default>
                <simple skill_id="WP_Item_kA_DA_57" skill_id_disable="false" />
                <transition>
                  <use_skill skill_id="WP_Item_kA_DA_57" next_combo_state="kComboStateDefault" />
                </transition>
              </combo_state_default>
            </default>
          </preset>
        </presets>
      </context>
      <context uid="12" feature_tag="BASE_LH" publisher_tag="ALL" min_skill_level="13" max_skill_level="13">
        <presets>
          <preset guid="954571381" is_toggle_slot="false">
            <default uid="0">
              <combo_state_default>
                <simple skill_id="WP_Item_kA_DA_57" skill_id_disable="false" />
                <transition>
                  <use_skill skill_id="WP_Item_kA_DA_57" next_combo_state="kComboStateDefault" />
                </transition>
              </combo_state_default>
            </default>
          </preset>
        </presets>
      </context>
      <context uid="13" feature_tag="BASE_LH" publisher_tag="ALL" min_skill_level="14" max_skill_level="14">
        <presets>
          <preset guid="954899063" is_toggle_slot="false">
            <default uid="0">
              <combo_state_default>
                <simple skill_id="WP_Item_kA_DA_57" skill_id_disable="false" />
                <transition>
                  <use_skill skill_id="WP_Item_kA_DA_57" next_combo_state="kComboStateDefault" />
                </transition>
              </combo_state_default>
            </default>
          </preset>
        </presets>
      </context>
      <context uid="14" feature_tag="BASE_LH" publisher_tag="ALL" min_skill_level="15" max_skill_level="15">
        <presets>
          <preset guid="954964600" is_toggle_slot="false">
            <default uid="0">
              <combo_state_default>
                <simple skill_id="WP_Item_kA_DA_57" skill_id_disable="false" />
                <transition>
                  <use_skill skill_id="WP_Item_kA_DA_57" next_combo_state="kComboStateDefault" />
                </transition>
              </combo_state_default>
            </default>
          </preset>
        </presets>
      </context>
      <context uid="15" feature_tag="BASE_LH" publisher_tag="ALL" min_skill_level="16" max_skill_level="16">
        <presets>
          <preset guid="954767993" is_toggle_slot="false">
            <default uid="0">
              <combo_state_default>
                <simple skill_id="WP_Item_kA_DA_57" skill_id_disable="false" />
                <transition>
                  <use_skill skill_id="WP_Item_kA_DA_57" next_combo_state="kComboStateDefault" />
                </transition>
              </combo_state_default>
            </default>
          </preset>
        </presets>
      </context>
      <context uid="16" feature_tag="BASE_LH" publisher_tag="ALL" min_skill_level="17" max_skill_level="17">
        <presets>
          <preset guid="954833530" is_toggle_slot="false">
            <default uid="0">
              <combo_state_default>
                <simple skill_id="WP_Item_kA_DA_57" skill_id_disable="false" />
                <transition>
                  <use_skill skill_id="WP_Item_kA_DA_57" next_combo_state="kComboStateDefault" />
                </transition>
              </combo_state_default>
            </default>
          </preset>
        </presets>
      </context>
      <context uid="17" feature_tag="BASE_LH" publisher_tag="ALL" min_skill_level="18" max_skill_level="18">
        <presets>
          <preset guid="955161211" is_toggle_slot="false">
            <default uid="0">
              <combo_state_default>
                <simple skill_id="WP_Item_kA_DA_57" skill_id_disable="false" />
                <transition>
                  <use_skill skill_id="WP_Item_kA_DA_57" next_combo_state="kComboStateDefault" />
                </transition>
              </combo_state_default>
            </default>
          </preset>
        </presets>
      </context>
      <context uid="18" feature_tag="BASE_LH" publisher_tag="ALL" min_skill_level="19" max_skill_level="19">
        <presets>
          <preset guid="955226792" is_toggle_slot="false">
            <default uid="0">
              <combo_state_default>
                <simple skill_id="WP_Item_kA_DA_57" skill_id_disable="false" />
                <transition>
                  <use_skill skill_id="WP_Item_kA_DA_57" next_combo_state="kComboStateDefault" />
                </transition>
              </combo_state_default>
            </default>
          </preset>
        </presets>
      </context>
      <context uid="19" feature_tag="BASE_LH" publisher_tag="ALL" min_skill_level="20" max_skill_level="20">
        <presets>
          <preset guid="955030186" is_toggle_slot="false">
            <default uid="0">
              <combo_state_default>
                <simple skill_id="WP_Item_kA_DA_57" skill_id_disable="false" />
                <transition>
                  <use_skill skill_id="WP_Item_kA_DA_57" next_combo_state="kComboStateDefault" />
                </transition>
              </combo_state_default>
            </default>
          </preset>
        </presets>
      </context>
      <trait_list />
    </skill_complex>
    <skill_complex guid="967177805" is_basic_attack="false" is_for_polymorphed_only="false" description="난폭한 기습 단검" unlock_level="1" id="SkillSet_WP_Item_A21_kA_DA" skill_enchant_category="kNone" skill_type="kPassiveSkill" feature_tag="BASE_LH" publisher_tag="ALL" skill_slot_affinity="kNotAssigned">
      <context uid="0" feature_tag="BASE_LH" publisher_tag="ALL" unlock_level="1" min_skill_level="1" max_skill_level="1">
        <presets>
          <preset guid="967112269" is_toggle_slot="false">
            <default uid="0">
              <combo_state_default>
                <simple skill_id="WP_Item_kA_DA_A21" skill_id_disable="false" />
                <transition>
                  <use_skill skill_id="WP_Item_kA_DA_A21" next_combo_state="kComboStateDefault" />
                </transition>
              </combo_state_default>
            </default>
          </preset>
        </presets>
      </context>
      <context uid="1" feature_tag="BASE_LH" publisher_tag="ALL" min_skill_level="2" max_skill_level="2">
        <presets>
          <preset guid="966522445" is_toggle_slot="false">
            <default uid="0">
              <combo_state_default>
                <simple skill_id="WP_Item_kA_DA_A21" skill_id_disable="false" />
                <transition>
                  <use_skill skill_id="WP_Item_kA_DA_A21" next_combo_state="kComboStateDefault" />
                </transition>
              </combo_state_default>
            </default>
          </preset>
        </presets>
      </context>
      <context uid="2" feature_tag="BASE_LH" publisher_tag="ALL" min_skill_level="3" max_skill_level="3">
        <presets>
          <preset guid="966456909" is_toggle_slot="false">
            <default uid="0">
              <combo_state_default>
                <simple skill_id="WP_Item_kA_DA_A21" skill_id_disable="false" />
                <transition>
                  <use_skill skill_id="WP_Item_kA_DA_A21" next_combo_state="kComboStateDefault" />
                </transition>
              </combo_state_default>
            </default>
          </preset>
        </presets>
      </context>
      <context uid="3" feature_tag="BASE_LH" publisher_tag="ALL" min_skill_level="4" max_skill_level="4">
        <presets>
          <preset guid="966391373" is_toggle_slot="false">
            <default uid="0">
              <combo_state_default>
                <simple skill_id="WP_Item_kA_DA_A21" skill_id_disable="false" />
                <transition>
                  <use_skill skill_id="WP_Item_kA_DA_A21" next_combo_state="kComboStateDefault" />
                </transition>
              </combo_state_default>
            </default>
          </preset>
        </presets>
      </context>
      <context uid="4" feature_tag="BASE_LH" publisher_tag="ALL" min_skill_level="5" max_skill_level="5">
        <presets>
          <preset guid="966325837" is_toggle_slot="false">
            <default uid="0">
              <combo_state_default>
                <simple skill_id="WP_Item_kA_DA_A21" skill_id_disable="false" />
                <transition>
                  <use_skill skill_id="WP_Item_kA_DA_A21" next_combo_state="kComboStateDefault" />
                </transition>
              </combo_state_default>
            </default>
          </preset>
        </presets>
      </context>
      <context uid="5" feature_tag="BASE_LH" publisher_tag="ALL" min_skill_level="6" max_skill_level="6">
        <presets>
          <preset guid="966784589" is_toggle_slot="false">
            <default uid="0">
              <combo_state_default>
                <simple skill_id="WP_Item_kA_DA_A21" skill_id_disable="false" />
                <transition>
                  <use_skill skill_id="WP_Item_kA_DA_A21" next_combo_state="kComboStateDefault" />
                </transition>
              </combo_state_default>
            </default>
          </preset>
        </presets>
      </context>
      <context uid="6" feature_tag="BASE_LH" publisher_tag="ALL" min_skill_level="7" max_skill_level="7">
        <presets>
          <preset guid="966719053" is_toggle_slot="false">
            <default uid="0">
              <combo_state_default>
                <simple skill_id="WP_Item_kA_DA_A21" skill_id_disable="false" />
                <transition>
                  <use_skill skill_id="WP_Item_kA_DA_A21" next_combo_state="kComboStateDefault" />
                </transition>
              </combo_state_default>
            </default>
          </preset>
        </presets>
      </context>
      <context uid="7" feature_tag="BASE_LH" publisher_tag="ALL" min_skill_level="8" max_skill_level="8">
        <presets>
          <preset guid="966653517" is_toggle_slot="false">
            <default uid="0">
              <combo_state_default>
                <simple skill_id="WP_Item_kA_DA_A21" skill_id_disable="false" />
                <transition>
                  <use_skill skill_id="WP_Item_kA_DA_A21" next_combo_state="kComboStateDefault" />
                </transition>
              </combo_state_default>
            </default>
          </preset>
        </presets>
      </context>
      <context uid="8" feature_tag="BASE_LH" publisher_tag="ALL" min_skill_level="9" max_skill_level="9">
        <presets>
          <preset guid="966587981" is_toggle_slot="false">
            <default uid="0">
              <combo_state_default>
                <simple skill_id="WP_Item_kA_DA_A21" skill_id_disable="false" />
                <transition>
                  <use_skill skill_id="WP_Item_kA_DA_A21" next_combo_state="kComboStateDefault" />
                </transition>
              </combo_state_default>
            </default>
          </preset>
        </presets>
      </context>
      <context uid="9" feature_tag="BASE_LH" publisher_tag="ALL" min_skill_level="10" max_skill_level="10">
        <presets>
          <preset guid="965998157" is_toggle_slot="false">
            <default uid="0">
              <combo_state_default>
                <simple skill_id="WP_Item_kA_DA_A21" skill_id_disable="false" />
                <transition>
                  <use_skill skill_id="WP_Item_kA_DA_A21" next_combo_state="kComboStateDefault" />
                </transition>
              </combo_state_default>
            </default>
          </preset>
        </presets>
      </context>
      <context uid="10" feature_tag="BASE_LH" publisher_tag="ALL" min_skill_level="11" max_skill_level="11">
        <presets>
          <preset guid="965932621" is_toggle_slot="false">
            <default uid="0">
              <combo_state_default>
                <simple skill_id="WP_Item_kA_DA_A21" skill_id_disable="false" />
                <transition>
                  <use_skill skill_id="WP_Item_kA_DA_A21" next_combo_state="kComboStateDefault" />
                </transition>
              </combo_state_default>
            </default>
          </preset>
        </presets>
      </context>
      <context uid="11" feature_tag="BASE_LH" publisher_tag="ALL" min_skill_level="12" max_skill_level="12">
        <presets>
          <preset guid="965867085" is_toggle_slot="false">
            <default uid="0">
              <combo_state_default>
                <simple skill_id="WP_Item_kA_DA_A21" skill_id_disable="false" />
                <transition>
                  <use_skill skill_id="WP_Item_kA_DA_A21" next_combo_state="kComboStateDefault" />
                </transition>
              </combo_state_default>
            </default>
          </preset>
        </presets>
      </context>
      <context uid="12" feature_tag="BASE_LH" publisher_tag="ALL" min_skill_level="13" max_skill_level="13">
        <presets>
          <preset guid="965801549" is_toggle_slot="false">
            <default uid="0">
              <combo_state_default>
                <simple skill_id="WP_Item_kA_DA_A21" skill_id_disable="false" />
                <transition>
                  <use_skill skill_id="WP_Item_kA_DA_A21" next_combo_state="kComboStateDefault" />
                </transition>
              </combo_state_default>
            </default>
          </preset>
        </presets>
      </context>
      <context uid="13" feature_tag="BASE_LH" publisher_tag="ALL" min_skill_level="14" max_skill_level="14">
        <presets>
          <preset guid="966260301" is_toggle_slot="false">
            <default uid="0">
              <combo_state_default>
                <simple skill_id="WP_Item_kA_DA_A21" skill_id_disable="false" />
                <transition>
                  <use_skill skill_id="WP_Item_kA_DA_A21" next_combo_state="kComboStateDefault" />
                </transition>
              </combo_state_default>
            </default>
          </preset>
        </presets>
      </context>
      <context uid="14" feature_tag="BASE_LH" publisher_tag="ALL" min_skill_level="15" max_skill_level="15">
        <presets>
          <preset guid="966194765" is_toggle_slot="false">
            <default uid="0">
              <combo_state_default>
                <simple skill_id="WP_Item_kA_DA_A21" skill_id_disable="false" />
                <transition>
                  <use_skill skill_id="WP_Item_kA_DA_A21" next_combo_state="kComboStateDefault" />
                </transition>
              </combo_state_default>
            </default>
          </preset>
        </presets>
      </context>
      <context uid="15" feature_tag="BASE_LH" publisher_tag="ALL" min_skill_level="16" max_skill_level="16">
        <presets>
          <preset guid="966129229" is_toggle_slot="false">
            <default uid="0">
              <combo_state_default>
                <simple skill_id="WP_Item_kA_DA_A21" skill_id_disable="false" />
                <transition>
                  <use_skill skill_id="WP_Item_kA_DA_A21" next_combo_state="kComboStateDefault" />
                </transition>
              </combo_state_default>
            </default>
          </preset>
        </presets>
      </context>
      <context uid="16" feature_tag="BASE_LH" publisher_tag="ALL" min_skill_level="17" max_skill_level="17">
        <presets>
          <preset guid="966063693" is_toggle_slot="false">
            <default uid="0">
              <combo_state_default>
                <simple skill_id="WP_Item_kA_DA_A21" skill_id_disable="false" />
                <transition>
                  <use_skill skill_id="WP_Item_kA_DA_A21" next_combo_state="kComboStateDefault" />
                </transition>
              </combo_state_default>
            </default>
          </preset>
        </presets>
      </context>
      <context uid="17" feature_tag="BASE_LH" publisher_tag="ALL" min_skill_level="18" max_skill_level="18">
        <presets>
          <preset guid="965473869" is_toggle_slot="false">
            <default uid="0">
              <combo_state_default>
                <simple skill_id="WP_Item_kA_DA_A21" skill_id_disable="false" />
                <transition>
                  <use_skill skill_id="WP_Item_kA_DA_A21" next_combo_state="kComboStateDefault" />
                </transition>
              </combo_state_default>
            </default>
          </preset>
        </presets>
      </context>
      <context uid="18" feature_tag="BASE_LH" publisher_tag="ALL" min_skill_level="19" max_skill_level="19">
        <presets>
          <preset guid="965408333" is_toggle_slot="false">
            <default uid="0">
              <combo_state_default>
                <simple skill_id="WP_Item_kA_DA_A21" skill_id_disable="false" />
                <transition>
                  <use_skill skill_id="WP_Item_kA_DA_A21" next_combo_state="kComboStateDefault" />
                </transition>
              </combo_state_default>
            </default>
          </preset>
        </presets>
      </context>
      <context uid="19" feature_tag="BASE_LH" publisher_tag="ALL" min_skill_level="20" max_skill_level="20">
        <presets>
          <preset guid="965342797" is_toggle_slot="false">
            <default uid="0">
              <combo_state_default>
                <simple skill_id="WP_Item_kA_DA_A21" skill_id_disable="false" />
                <transition>
                  <use_skill skill_id="WP_Item_kA_DA_A21" next_combo_state="kComboStateDefault" />
                </transition>
              </combo_state_default>
            </default>
          </preset>
        </presets>
      </context>
      <trait_list />
    </skill_complex>
    <skill_complex guid="961934905" is_basic_attack="false" is_for_polymorphed_only="false" description="마인제로크의 단검" unlock_level="1" id="SkillSet_WP_Item_A04_kA_DA" skill_enchant_category="kNone" skill_type="kPassiveSkill" feature_tag="BASE_LH" publisher_tag="ALL" skill_slot_affinity="kNotAssigned">
      <context uid="0" feature_tag="BASE_LH" publisher_tag="ALL" unlock_level="1" min_skill_level="1" max_skill_level="1">
        <presets>
          <preset guid="961869369" is_toggle_slot="false">
            <default uid="0">
              <combo_state_default>
                <simple skill_id="WP_Item_kA_DA_A04" skill_id_disable="false" />
                <transition>
                  <use_skill skill_id="WP_Item_kA_DA_A04" next_combo_state="kComboStateDefault" />
                </transition>
              </combo_state_default>
            </default>
          </preset>
        </presets>
      </context>
      <context uid="1" feature_tag="BASE_LH" publisher_tag="ALL" min_skill_level="2" max_skill_level="2">
        <presets>
          <preset guid="961279545" is_toggle_slot="false">
            <default uid="0">
              <combo_state_default>
                <simple skill_id="WP_Item_kA_DA_A04" skill_id_disable="false" />
                <transition>
                  <use_skill skill_id="WP_Item_kA_DA_A04" next_combo_state="kComboStateDefault" />
                </transition>
              </combo_state_default>
            </default>
          </preset>
        </presets>
      </context>
      <context uid="2" feature_tag="BASE_LH" publisher_tag="ALL" min_skill_level="3" max_skill_level="3">
        <presets>
          <preset guid="961214009" is_toggle_slot="false">
            <default uid="0">
              <combo_state_default>
                <simple skill_id="WP_Item_kA_DA_A04" skill_id_disable="false" />
                <transition>
                  <use_skill skill_id="WP_Item_kA_DA_A04" next_combo_state="kComboStateDefault" />
                </transition>
              </combo_state_default>
            </default>
          </preset>
        </presets>
      </context>
      <context uid="3" feature_tag="BASE_LH" publisher_tag="ALL" min_skill_level="4" max_skill_level="4">
        <presets>
          <preset guid="961148473" is_toggle_slot="false">
            <default uid="0">
              <combo_state_default>
                <simple skill_id="WP_Item_kA_DA_A04" skill_id_disable="false" />
                <transition>
                  <use_skill skill_id="WP_Item_kA_DA_A04" next_combo_state="kComboStateDefault" />
                </transition>
              </combo_state_default>
            </default>
          </preset>
        </presets>
      </context>
      <context uid="4" feature_tag="BASE_LH" publisher_tag="ALL" min_skill_level="5" max_skill_level="5">
        <presets>
          <preset guid="961082937" is_toggle_slot="false">
            <default uid="0">
              <combo_state_default>
                <simple skill_id="WP_Item_kA_DA_A04" skill_id_disable="false" />
                <transition>
                  <use_skill skill_id="WP_Item_kA_DA_A04" next_combo_state="kComboStateDefault" />
                </transition>
              </combo_state_default>
            </default>
          </preset>
        </presets>
      </context>
      <context uid="5" feature_tag="BASE_LH" publisher_tag="ALL" min_skill_level="6" max_skill_level="6">
        <presets>
          <preset guid="961541689" is_toggle_slot="false">
            <default uid="0">
              <combo_state_default>
                <simple skill_id="WP_Item_kA_DA_A04" skill_id_disable="false" />
                <transition>
                  <use_skill skill_id="WP_Item_kA_DA_A04" next_combo_state="kComboStateDefault" />
                </transition>
              </combo_state_default>
            </default>
          </preset>
        </presets>
      </context>
      <context uid="6" feature_tag="BASE_LH" publisher_tag="ALL" min_skill_level="7" max_skill_level="7">
        <presets>
          <preset guid="961476153" is_toggle_slot="false">
            <default uid="0">
              <combo_state_default>
                <simple skill_id="WP_Item_kA_DA_A04" skill_id_disable="false" />
                <transition>
                  <use_skill skill_id="WP_Item_kA_DA_A04" next_combo_state="kComboStateDefault" />
                </transition>
              </combo_state_default>
            </default>
          </preset>
        </presets>
      </context>
      <context uid="7" feature_tag="BASE_LH" publisher_tag="ALL" min_skill_level="8" max_skill_level="8">
        <presets>
          <preset guid="961410617" is_toggle_slot="false">
            <default uid="0">
              <combo_state_default>
                <simple skill_id="WP_Item_kA_DA_A04" skill_id_disable="false" />
                <transition>
                  <use_skill skill_id="WP_Item_kA_DA_A04" next_combo_state="kComboStateDefault" />
                </transition>
              </combo_state_default>
            </default>
          </preset>
        </presets>
      </context>
      <context uid="8" feature_tag="BASE_LH" publisher_tag="ALL" min_skill_level="9" max_skill_level="9">
        <presets>
          <preset guid="961345081" is_toggle_slot="false">
            <default uid="0">
              <combo_state_default>
                <simple skill_id="WP_Item_kA_DA_A04" skill_id_disable="false" />
                <transition>
                  <use_skill skill_id="WP_Item_kA_DA_A04" next_combo_state="kComboStateDefault" />
                </transition>
              </combo_state_default>
            </default>
          </preset>
        </presets>
      </context>
      <context uid="9" feature_tag="BASE_LH" publisher_tag="ALL" min_skill_level="10" max_skill_level="10">
        <presets>
          <preset guid="960755257" is_toggle_slot="false">
            <default uid="0">
              <combo_state_default>
                <simple skill_id="WP_Item_kA_DA_A04" skill_id_disable="false" />
                <transition>
                  <use_skill skill_id="WP_Item_kA_DA_A04" next_combo_state="kComboStateDefault" />
                </transition>
              </combo_state_default>
            </default>
          </preset>
        </presets>
      </context>
      <context uid="10" feature_tag="BASE_LH" publisher_tag="ALL" min_skill_level="11" max_skill_level="11">
        <presets>
          <preset guid="960689721" is_toggle_slot="false">
            <default uid="0">
              <combo_state_default>
                <simple skill_id="WP_Item_kA_DA_A04" skill_id_disable="false" />
                <transition>
                  <use_skill skill_id="WP_Item_kA_DA_A04" next_combo_state="kComboStateDefault" />
                </transition>
              </combo_state_default>
            </default>
          </preset>
        </presets>
      </context>
      <context uid="11" feature_tag="BASE_LH" publisher_tag="ALL" min_skill_level="12" max_skill_level="12">
        <presets>
          <preset guid="960624185" is_toggle_slot="false">
            <default uid="0">
              <combo_state_default>
                <simple skill_id="WP_Item_kA_DA_A04" skill_id_disable="false" />
                <transition>
                  <use_skill skill_id="WP_Item_kA_DA_A04" next_combo_state="kComboStateDefault" />
                </transition>
              </combo_state_default>
            </default>
          </preset>
        </presets>
      </context>
      <context uid="12" feature_tag="BASE_LH" publisher_tag="ALL" min_skill_level="13" max_skill_level="13">
        <presets>
          <preset guid="960558649" is_toggle_slot="false">
            <default uid="0">
              <combo_state_default>
                <simple skill_id="WP_Item_kA_DA_A04" skill_id_disable="false" />
                <transition>
                  <use_skill skill_id="WP_Item_kA_DA_A04" next_combo_state="kComboStateDefault" />
                </transition>
              </combo_state_default>
            </default>
          </preset>
        </presets>
      </context>
      <context uid="13" feature_tag="BASE_LH" publisher_tag="ALL" min_skill_level="14" max_skill_level="14">
        <presets>
          <preset guid="961017401" is_toggle_slot="false">
            <default uid="0">
              <combo_state_default>
                <simple skill_id="WP_Item_kA_DA_A04" skill_id_disable="false" />
                <transition>
                  <use_skill skill_id="WP_Item_kA_DA_A04" next_combo_state="kComboStateDefault" />
                </transition>
              </combo_state_default>
            </default>
          </preset>
        </presets>
      </context>
      <context uid="14" feature_tag="BASE_LH" publisher_tag="ALL" min_skill_level="15" max_skill_level="15">
        <presets>
          <preset guid="960951865" is_toggle_slot="false">
            <default uid="0">
              <combo_state_default>
                <simple skill_id="WP_Item_kA_DA_A04" skill_id_disable="false" />
                <transition>
                  <use_skill skill_id="WP_Item_kA_DA_A04" next_combo_state="kComboStateDefault" />
                </transition>
              </combo_state_default>
            </default>
          </preset>
        </presets>
      </context>
      <context uid="15" feature_tag="BASE_LH" publisher_tag="ALL" min_skill_level="16" max_skill_level="16">
        <presets>
          <preset guid="960886329" is_toggle_slot="false">
            <default uid="0">
              <combo_state_default>
                <simple skill_id="WP_Item_kA_DA_A04" skill_id_disable="false" />
                <transition>
                  <use_skill skill_id="WP_Item_kA_DA_A04" next_combo_state="kComboStateDefault" />
                </transition>
              </combo_state_default>
            </default>
          </preset>
        </presets>
      </context>
      <context uid="16" feature_tag="BASE_LH" publisher_tag="ALL" min_skill_level="17" max_skill_level="17">
        <presets>
          <preset guid="960820793" is_toggle_slot="false">
            <default uid="0">
              <combo_state_default>
                <simple skill_id="WP_Item_kA_DA_A04" skill_id_disable="false" />
                <transition>
                  <use_skill skill_id="WP_Item_kA_DA_A04" next_combo_state="kComboStateDefault" />
                </transition>
              </combo_state_default>
            </default>
          </preset>
        </presets>
      </context>
      <context uid="17" feature_tag="BASE_LH" publisher_tag="ALL" min_skill_level="18" max_skill_level="18">
        <presets>
          <preset guid="960230969" is_toggle_slot="false">
            <default uid="0">
              <combo_state_default>
                <simple skill_id="WP_Item_kA_DA_A04" skill_id_disable="false" />
                <transition>
                  <use_skill skill_id="WP_Item_kA_DA_A04" next_combo_state="kComboStateDefault" />
                </transition>
              </combo_state_default>
            </default>
          </preset>
        </presets>
      </context>
      <context uid="18" feature_tag="BASE_LH" publisher_tag="ALL" min_skill_level="19" max_skill_level="19">
        <presets>
          <preset guid="960165433" is_toggle_slot="false">
            <default uid="0">
              <combo_state_default>
                <simple skill_id="WP_Item_kA_DA_A04" skill_id_disable="false" />
                <transition>
                  <use_skill skill_id="WP_Item_kA_DA_A04" next_combo_state="kComboStateDefault" />
                </transition>
              </combo_state_default>
            </default>
          </preset>
        </presets>
      </context>
      <context uid="19" feature_tag="BASE_LH" publisher_tag="ALL" min_skill_level="20" max_skill_level="20">
        <presets>
          <preset guid="960099897" is_toggle_slot="false">
            <default uid="0">
              <combo_state_default>
                <simple skill_id="WP_Item_kA_DA_A04" skill_id_disable="false" />
                <transition>
                  <use_skill skill_id="WP_Item_kA_DA_A04" next_combo_state="kComboStateDefault" />
                </transition>
              </combo_state_default>
            </default>
          </preset>
        </presets>
      </context>
      <trait_list />
    </skill_complex>
    <skill_complex guid="948858721" is_basic_attack="false" is_for_polymorphed_only="false" description="코완주키의 황혼도" unlock_level="1" id="SkillSet_WP_Item_kA_DA_61_2" skill_enchant_category="kNone" skill_type="kPassiveSkill" feature_tag="BASE_LH" publisher_tag="ALL" skill_slot_affinity="kNotAssigned">
      <context uid="0" unlock_level="1" feature_tag="BASE_LH" publisher_tag="ALL" min_skill_level="1" max_skill_level="1">
        <presets>
          <preset guid="948924257" is_toggle_slot="false">
            <default uid="0">
              <combo_state_default>
                <simple skill_id="WP_Item_kA_DA_61_2" skill_id_disable="false" />
                <transition>
                  <use_skill skill_id="WP_Item_kA_DA_61_2" next_combo_state="kComboStateDefault" />
                </transition>
              </combo_state_default>
            </default>
          </preset>
        </presets>
      </context>
      <context uid="1" feature_tag="BASE_LH" publisher_tag="ALL" min_skill_level="2" max_skill_level="2">
        <presets>
          <preset guid="949303257" is_toggle_slot="false">
            <default uid="0">
              <combo_state_default>
                <simple skill_id="WP_Item_kA_DA_61_2" skill_id_disable="false" />
                <transition>
                  <use_skill skill_id="WP_Item_kA_DA_61_2" next_combo_state="kComboStateDefault" />
                </transition>
              </combo_state_default>
            </default>
          </preset>
        </presets>
      </context>
      <context uid="2" feature_tag="BASE_LH" publisher_tag="ALL" min_skill_level="3" max_skill_level="3">
        <presets>
          <preset guid="949368798" is_toggle_slot="false">
            <default uid="0">
              <combo_state_default>
                <simple skill_id="WP_Item_kA_DA_61_2" skill_id_disable="false" />
                <transition>
                  <use_skill skill_id="WP_Item_kA_DA_61_2" next_combo_state="kComboStateDefault" />
                </transition>
              </combo_state_default>
            </default>
          </preset>
        </presets>
      </context>
      <context uid="3" feature_tag="BASE_LH" publisher_tag="ALL" min_skill_level="4" max_skill_level="4">
        <presets>
          <preset guid="949434334" is_toggle_slot="false">
            <default uid="0">
              <combo_state_default>
                <simple skill_id="WP_Item_kA_DA_61_2" skill_id_disable="false" />
                <transition>
                  <use_skill skill_id="WP_Item_kA_DA_61_2" next_combo_state="kComboStateDefault" />
                </transition>
              </combo_state_default>
            </default>
          </preset>
        </presets>
      </context>
      <context uid="4" feature_tag="BASE_LH" publisher_tag="ALL" min_skill_level="5" max_skill_level="5">
        <presets>
          <preset guid="948975583" is_toggle_slot="false">
            <default uid="0">
              <combo_state_default>
                <simple skill_id="WP_Item_kA_DA_61_2" skill_id_disable="false" />
                <transition>
                  <use_skill skill_id="WP_Item_kA_DA_61_2" next_combo_state="kComboStateDefault" />
                </transition>
              </combo_state_default>
            </default>
          </preset>
        </presets>
      </context>
      <context uid="5" feature_tag="BASE_LH" publisher_tag="ALL" min_skill_level="6" max_skill_level="6">
        <presets>
          <preset guid="953981949" is_toggle_slot="false">
            <default uid="0">
              <combo_state_default>
                <simple skill_id="WP_Item_kA_DA_61_2" skill_id_disable="false" />
                <transition>
                  <use_skill skill_id="WP_Item_kA_DA_61_2" next_combo_state="kComboStateDefault" />
                </transition>
              </combo_state_default>
            </default>
          </preset>
        </presets>
      </context>
      <context uid="6" feature_tag="BASE_LH" publisher_tag="ALL" min_skill_level="7" max_skill_level="7">
        <presets>
          <preset guid="954047486" is_toggle_slot="false">
            <default uid="0">
              <combo_state_default>
                <simple skill_id="WP_Item_kA_DA_61_2" skill_id_disable="false" />
                <transition>
                  <use_skill skill_id="WP_Item_kA_DA_61_2" next_combo_state="kComboStateDefault" />
                </transition>
              </combo_state_default>
            </default>
          </preset>
        </presets>
      </context>
      <context uid="7" feature_tag="BASE_LH" publisher_tag="ALL" min_skill_level="8" max_skill_level="8">
        <presets>
          <preset guid="952278015" is_toggle_slot="false">
            <default uid="0">
              <combo_state_default>
                <simple skill_id="WP_Item_kA_DA_61_2" skill_id_disable="false" />
                <transition>
                  <use_skill skill_id="WP_Item_kA_DA_61_2" next_combo_state="kComboStateDefault" />
                </transition>
              </combo_state_default>
            </default>
          </preset>
        </presets>
      </context>
      <context uid="8" feature_tag="BASE_LH" publisher_tag="ALL" min_skill_level="9" max_skill_level="9">
        <presets>
          <preset guid="952343552" is_toggle_slot="false">
            <default uid="0">
              <combo_state_default>
                <simple skill_id="WP_Item_kA_DA_61_2" skill_id_disable="false" />
                <transition>
                  <use_skill skill_id="WP_Item_kA_DA_61_2" next_combo_state="kComboStateDefault" />
                </transition>
              </combo_state_default>
            </default>
          </preset>
        </presets>
      </context>
      <context uid="9" feature_tag="BASE_LH" publisher_tag="ALL" min_skill_level="10" max_skill_level="10">
        <presets>
          <preset guid="952146945" is_toggle_slot="false">
            <default uid="0">
              <combo_state_default>
                <simple skill_id="WP_Item_kA_DA_61_2" skill_id_disable="false" />
                <transition>
                  <use_skill skill_id="WP_Item_kA_DA_61_2" next_combo_state="kComboStateDefault" />
                </transition>
              </combo_state_default>
            </default>
          </preset>
        </presets>
      </context>
      <context uid="10" feature_tag="BASE_LH" publisher_tag="ALL" min_skill_level="11" max_skill_level="11">
        <presets>
          <preset guid="952212482" is_toggle_slot="false">
            <default uid="0">
              <combo_state_default>
                <simple skill_id="WP_Item_kA_DA_61_2" skill_id_disable="false" />
                <transition>
                  <use_skill skill_id="WP_Item_kA_DA_61_2" next_combo_state="kComboStateDefault" />
                </transition>
              </combo_state_default>
            </default>
          </preset>
        </presets>
      </context>
      <context uid="11" feature_tag="BASE_LH" publisher_tag="ALL" min_skill_level="12" max_skill_level="12">
        <presets>
          <preset guid="952540163" is_toggle_slot="false">
            <default uid="0">
              <combo_state_default>
                <simple skill_id="WP_Item_kA_DA_61_2" skill_id_disable="false" />
                <transition>
                  <use_skill skill_id="WP_Item_kA_DA_61_2" next_combo_state="kComboStateDefault" />
                </transition>
              </combo_state_default>
            </default>
          </preset>
        </presets>
      </context>
      <context uid="12" feature_tag="BASE_LH" publisher_tag="ALL" min_skill_level="13" max_skill_level="13">
        <presets>
          <preset guid="952605700" is_toggle_slot="false">
            <default uid="0">
              <combo_state_default>
                <simple skill_id="WP_Item_kA_DA_61_2" skill_id_disable="false" />
                <transition>
                  <use_skill skill_id="WP_Item_kA_DA_61_2" next_combo_state="kComboStateDefault" />
                </transition>
              </combo_state_default>
            </default>
          </preset>
        </presets>
      </context>
      <context uid="13" feature_tag="BASE_LH" publisher_tag="ALL" min_skill_level="14" max_skill_level="14">
        <presets>
          <preset guid="952409093" is_toggle_slot="false">
            <default uid="0">
              <combo_state_default>
                <simple skill_id="WP_Item_kA_DA_61_2" skill_id_disable="false" />
                <transition>
                  <use_skill skill_id="WP_Item_kA_DA_61_2" next_combo_state="kComboStateDefault" />
                </transition>
              </combo_state_default>
            </default>
          </preset>
        </presets>
      </context>
      <context uid="14" feature_tag="BASE_LH" publisher_tag="ALL" min_skill_level="15" max_skill_level="15">
        <presets>
          <preset guid="952474630" is_toggle_slot="false">
            <default uid="0">
              <combo_state_default>
                <simple skill_id="WP_Item_kA_DA_61_2" skill_id_disable="false" />
                <transition>
                  <use_skill skill_id="WP_Item_kA_DA_61_2" next_combo_state="kComboStateDefault" />
                </transition>
              </combo_state_default>
            </default>
          </preset>
        </presets>
      </context>
      <context uid="15" feature_tag="BASE_LH" publisher_tag="ALL" min_skill_level="16" max_skill_level="16">
        <presets>
          <preset guid="952802311" is_toggle_slot="false">
            <default uid="0">
              <combo_state_default>
                <simple skill_id="WP_Item_kA_DA_61_2" skill_id_disable="false" />
                <transition>
                  <use_skill skill_id="WP_Item_kA_DA_61_2" next_combo_state="kComboStateDefault" />
                </transition>
              </combo_state_default>
            </default>
          </preset>
        </presets>
      </context>
      <context uid="16" feature_tag="BASE_LH" publisher_tag="ALL" min_skill_level="17" max_skill_level="17">
        <presets>
          <preset guid="952867848" is_toggle_slot="false">
            <default uid="0">
              <combo_state_default>
                <simple skill_id="WP_Item_kA_DA_61_2" skill_id_disable="false" />
                <transition>
                  <use_skill skill_id="WP_Item_kA_DA_61_2" next_combo_state="kComboStateDefault" />
                </transition>
              </combo_state_default>
            </default>
          </preset>
        </presets>
      </context>
      <context uid="17" feature_tag="BASE_LH" publisher_tag="ALL" min_skill_level="18" max_skill_level="18">
        <presets>
          <preset guid="952671241" is_toggle_slot="false">
            <default uid="0">
              <combo_state_default>
                <simple skill_id="WP_Item_kA_DA_61_2" skill_id_disable="false" />
                <transition>
                  <use_skill skill_id="WP_Item_kA_DA_61_2" next_combo_state="kComboStateDefault" />
                </transition>
              </combo_state_default>
            </default>
          </preset>
        </presets>
      </context>
      <context uid="18" feature_tag="BASE_LH" publisher_tag="ALL" min_skill_level="19" max_skill_level="19">
        <presets>
          <preset guid="952736778" is_toggle_slot="false">
            <default uid="0">
              <combo_state_default>
                <simple skill_id="WP_Item_kA_DA_61_2" skill_id_disable="false" />
                <transition>
                  <use_skill skill_id="WP_Item_kA_DA_61_2" next_combo_state="kComboStateDefault" />
                </transition>
              </combo_state_default>
            </default>
          </preset>
        </presets>
      </context>
      <context uid="19" feature_tag="BASE_LH" publisher_tag="ALL" min_skill_level="20" max_skill_level="20">
        <presets>
          <preset guid="953064459" is_toggle_slot="false">
            <default uid="0">
              <combo_state_default>
                <simple skill_id="WP_Item_kA_DA_61_2" skill_id_disable="false" />
                <transition>
                  <use_skill skill_id="WP_Item_kA_DA_61_2" next_combo_state="kComboStateDefault" />
                </transition>
              </combo_state_default>
            </default>
          </preset>
        </presets>
      </context>
      <trait_list />
    </skill_complex>
    <skill_complex guid="950019250" is_basic_attack="false" is_for_polymorphed_only="false" description="전설 미사용" unlock_level="1" id="SkillSet_WP_Item_kAAA_DA_60" skill_enchant_category="kNone" skill_type="kActiveSkill" feature_tag="BASE_LH" publisher_tag="ALL" skill_slot_affinity="kNotAssigned">
      <context uid="0" unlock_level="1" feature_tag="BASE_LH" publisher_tag="ALL" min_skill_level="1" max_skill_level="1">
        <presets>
          <preset guid="950084786" is_toggle_slot="false">
            <default uid="0">
              <combo_state_default>
                <simple skill_id="WP_Item_kAAA_DA_60" skill_id_disable="false" />
                <transition>
                  <use_skill skill_id="WP_Item_kAAA_DA_60" next_combo_state="kComboStateDefault" />
                </transition>
              </combo_state_default>
            </default>
          </preset>
        </presets>
      </context>
      <context uid="1" feature_tag="BASE_LH" publisher_tag="ALL" min_skill_level="2" max_skill_level="2">
        <presets>
          <preset guid="943012839" is_toggle_slot="false">
            <default uid="0">
              <combo_state_default>
                <simple skill_id="WP_Item_kAAA_DA_60" skill_id_disable="false" />
                <transition>
                  <use_skill skill_id="WP_Item_kAAA_DA_60" next_combo_state="kComboStateDefault" />
                </transition>
              </combo_state_default>
            </default>
          </preset>
        </presets>
      </context>
      <context uid="2" feature_tag="BASE_LH" publisher_tag="ALL" min_skill_level="3" max_skill_level="3">
        <presets>
          <preset guid="943078383" is_toggle_slot="false">
            <default uid="0">
              <combo_state_default>
                <simple skill_id="WP_Item_kAAA_DA_60" skill_id_disable="false" />
                <transition>
                  <use_skill skill_id="WP_Item_kAAA_DA_60" next_combo_state="kComboStateDefault" />
                </transition>
              </combo_state_default>
            </default>
          </preset>
        </presets>
      </context>
      <context uid="3" feature_tag="BASE_LH" publisher_tag="ALL" min_skill_level="4" max_skill_level="4">
        <presets>
          <preset guid="943143923" is_toggle_slot="false">
            <default uid="0">
              <combo_state_default>
                <simple skill_id="WP_Item_kAAA_DA_60" skill_id_disable="false" />
                <transition>
                  <use_skill skill_id="WP_Item_kAAA_DA_60" next_combo_state="kComboStateDefault" />
                </transition>
              </combo_state_default>
            </default>
          </preset>
        </presets>
      </context>
      <context uid="4" feature_tag="BASE_LH" publisher_tag="ALL" min_skill_level="5" max_skill_level="5">
        <presets>
          <preset guid="942685172" is_toggle_slot="false">
            <default uid="0">
              <combo_state_default>
                <simple skill_id="WP_Item_kAAA_DA_60" skill_id_disable="false" />
                <transition>
                  <use_skill skill_id="WP_Item_kAAA_DA_60" next_combo_state="kComboStateDefault" />
                </transition>
              </combo_state_default>
            </default>
          </preset>
        </presets>
      </context>
      <context uid="5" feature_tag="BASE_LH" publisher_tag="ALL" min_skill_level="6" max_skill_level="6">
        <presets>
          <preset guid="969153412" is_toggle_slot="false">
            <default uid="0">
              <combo_state_default>
                <simple skill_id="WP_Item_kAAA_DA_60" skill_id_disable="false" />
                <transition>
                  <use_skill skill_id="WP_Item_kAAA_DA_60" next_combo_state="kComboStateDefault" />
                </transition>
              </combo_state_default>
            </default>
          </preset>
        </presets>
      </context>
      <context uid="6" feature_tag="BASE_LH" publisher_tag="ALL" min_skill_level="7" max_skill_level="7">
        <presets>
          <preset guid="972757893" is_toggle_slot="false">
            <default uid="0">
              <combo_state_default>
                <simple skill_id="WP_Item_kAAA_DA_60" skill_id_disable="false" />
                <transition>
                  <use_skill skill_id="WP_Item_kAAA_DA_60" next_combo_state="kComboStateDefault" />
                </transition>
              </combo_state_default>
            </default>
          </preset>
        </presets>
      </context>
      <context uid="7" feature_tag="BASE_LH" publisher_tag="ALL" min_skill_level="8" max_skill_level="8">
        <presets>
          <preset guid="972692358" is_toggle_slot="false">
            <default uid="0">
              <combo_state_default>
                <simple skill_id="WP_Item_kAAA_DA_60" skill_id_disable="false" />
                <transition>
                  <use_skill skill_id="WP_Item_kAAA_DA_60" next_combo_state="kComboStateDefault" />
                </transition>
              </combo_state_default>
            </default>
          </preset>
        </presets>
      </context>
      <context uid="8" feature_tag="BASE_LH" publisher_tag="ALL" min_skill_level="9" max_skill_level="9">
        <presets>
          <preset guid="972626823" is_toggle_slot="false">
            <default uid="0">
              <combo_state_default>
                <simple skill_id="WP_Item_kAAA_DA_60" skill_id_disable="false" />
                <transition>
                  <use_skill skill_id="WP_Item_kAAA_DA_60" next_combo_state="kComboStateDefault" />
                </transition>
              </combo_state_default>
            </default>
          </preset>
        </presets>
      </context>
      <context uid="9" feature_tag="BASE_LH" publisher_tag="ALL" min_skill_level="10" max_skill_level="10">
        <presets>
          <preset guid="972561288" is_toggle_slot="false">
            <default uid="0">
              <combo_state_default>
                <simple skill_id="WP_Item_kAAA_DA_60" skill_id_disable="false" />
                <transition>
                  <use_skill skill_id="WP_Item_kAAA_DA_60" next_combo_state="kComboStateDefault" />
                </transition>
              </combo_state_default>
            </default>
          </preset>
        </presets>
      </context>
      <context uid="10" feature_tag="BASE_LH" publisher_tag="ALL" min_skill_level="11" max_skill_level="11">
        <presets>
          <preset guid="973020041" is_toggle_slot="false">
            <default uid="0">
              <combo_state_default>
                <simple skill_id="WP_Item_kAAA_DA_60" skill_id_disable="false" />
                <transition>
                  <use_skill skill_id="WP_Item_kAAA_DA_60" next_combo_state="kComboStateDefault" />
                </transition>
              </combo_state_default>
            </default>
          </preset>
        </presets>
      </context>
      <context uid="11" feature_tag="BASE_LH" publisher_tag="ALL" min_skill_level="12" max_skill_level="12">
        <presets>
          <preset guid="972954506" is_toggle_slot="false">
            <default uid="0">
              <combo_state_default>
                <simple skill_id="WP_Item_kAAA_DA_60" skill_id_disable="false" />
                <transition>
                  <use_skill skill_id="WP_Item_kAAA_DA_60" next_combo_state="kComboStateDefault" />
                </transition>
              </combo_state_default>
            </default>
          </preset>
        </presets>
      </context>
      <context uid="12" feature_tag="BASE_LH" publisher_tag="ALL" min_skill_level="13" max_skill_level="13">
        <presets>
          <preset guid="972888971" is_toggle_slot="false">
            <default uid="0">
              <combo_state_default>
                <simple skill_id="WP_Item_kAAA_DA_60" skill_id_disable="false" />
                <transition>
                  <use_skill skill_id="WP_Item_kAAA_DA_60" next_combo_state="kComboStateDefault" />
                </transition>
              </combo_state_default>
            </default>
          </preset>
        </presets>
      </context>
      <context uid="13" feature_tag="BASE_LH" publisher_tag="ALL" min_skill_level="14" max_skill_level="14">
        <presets>
          <preset guid="972823437" is_toggle_slot="false">
            <default uid="0">
              <combo_state_default>
                <simple skill_id="WP_Item_kAAA_DA_60" skill_id_disable="false" />
                <transition>
                  <use_skill skill_id="WP_Item_kAAA_DA_60" next_combo_state="kComboStateDefault" />
                </transition>
              </combo_state_default>
            </default>
          </preset>
        </presets>
      </context>
      <context uid="14" feature_tag="BASE_LH" publisher_tag="ALL" min_skill_level="15" max_skill_level="15">
        <presets>
          <preset guid="972233613" is_toggle_slot="false">
            <default uid="0">
              <combo_state_default>
                <simple skill_id="WP_Item_kAAA_DA_60" skill_id_disable="false" />
                <transition>
                  <use_skill skill_id="WP_Item_kAAA_DA_60" next_combo_state="kComboStateDefault" />
                </transition>
              </combo_state_default>
            </default>
          </preset>
        </presets>
      </context>
      <context uid="15" feature_tag="BASE_LH" publisher_tag="ALL" min_skill_level="16" max_skill_level="16">
        <presets>
          <preset guid="972168078" is_toggle_slot="false">
            <default uid="0">
              <combo_state_default>
                <simple skill_id="WP_Item_kAAA_DA_60" skill_id_disable="false" />
                <transition>
                  <use_skill skill_id="WP_Item_kAAA_DA_60" next_combo_state="kComboStateDefault" />
                </transition>
              </combo_state_default>
            </default>
          </preset>
        </presets>
      </context>
      <context uid="16" feature_tag="BASE_LH" publisher_tag="ALL" min_skill_level="17" max_skill_level="17">
        <presets>
          <preset guid="972102543" is_toggle_slot="false">
            <default uid="0">
              <combo_state_default>
                <simple skill_id="WP_Item_kAAA_DA_60" skill_id_disable="false" />
                <transition>
                  <use_skill skill_id="WP_Item_kAAA_DA_60" next_combo_state="kComboStateDefault" />
                </transition>
              </combo_state_default>
            </default>
          </preset>
        </presets>
      </context>
      <context uid="17" feature_tag="BASE_LH" publisher_tag="ALL" min_skill_level="18" max_skill_level="18">
        <presets>
          <preset guid="972037008" is_toggle_slot="false">
            <default uid="0">
              <combo_state_default>
                <simple skill_id="WP_Item_kAAA_DA_60" skill_id_disable="false" />
                <transition>
                  <use_skill skill_id="WP_Item_kAAA_DA_60" next_combo_state="kComboStateDefault" />
                </transition>
              </combo_state_default>
            </default>
          </preset>
        </presets>
      </context>
      <context uid="18" feature_tag="BASE_LH" publisher_tag="ALL" min_skill_level="19" max_skill_level="19">
        <presets>
          <preset guid="972495761" is_toggle_slot="false">
            <default uid="0">
              <combo_state_default>
                <simple skill_id="WP_Item_kAAA_DA_60" skill_id_disable="false" />
                <transition>
                  <use_skill skill_id="WP_Item_kAAA_DA_60" next_combo_state="kComboStateDefault" />
                </transition>
              </combo_state_default>
            </default>
          </preset>
        </presets>
      </context>
      <context uid="19" feature_tag="BASE_LH" publisher_tag="ALL" min_skill_level="20" max_skill_level="20">
        <presets>
          <preset guid="972430226" is_toggle_slot="false">
            <default uid="0">
              <combo_state_default>
                <simple skill_id="WP_Item_kAAA_DA_60" skill_id_disable="false" />
                <transition>
                  <use_skill skill_id="WP_Item_kAAA_DA_60" next_combo_state="kComboStateDefault" />
                </transition>
              </combo_state_default>
            </default>
          </preset>
        </presets>
      </context>
      <trait_list />
    </skill_complex>
    <skill_complex guid="940283132" is_basic_attack="false" is_for_polymorphed_only="false" description="네르자툼 단검" unlock_level="1" id="SkillSet_WP_Item_Boss_T3_DA_01" skill_enchant_category="kNone" skill_type="kPassiveSkill" feature_tag="BASE_LH" publisher_tag="ALL" skill_slot_affinity="kNotAssigned">
      <context uid="0" feature_tag="BASE_LH" publisher_tag="ALL" unlock_level="1" min_skill_level="1" max_skill_level="1">
        <presets>
          <preset guid="940217596" is_toggle_slot="false">
            <default uid="0">
              <combo_state_default>
                <simple skill_id="WP_Item_Boss_T3_DA_01" skill_id_disable="false" />
                <transition>
                  <use_skill skill_id="WP_Item_Boss_T3_DA_01" next_combo_state="kComboStateDefault" />
                </transition>
              </combo_state_default>
            </default>
          </preset>
        </presets>
      </context>
      <trait_list />
    </skill_complex>
    <skill_complex guid="940545434" is_basic_attack="false" is_for_polymorphed_only="false" description="마인제로크 단검 t3" unlock_level="1" id="SkillSet_WP_Item_FieldBoss_T3_DA_01" skill_enchant_category="kNone" skill_type="kPassiveSkill" feature_tag="BASE_LH" publisher_tag="ALL" skill_slot_affinity="kNotAssigned">
      <context uid="0" feature_tag="BASE_LH" publisher_tag="ALL" unlock_level="1" min_skill_level="1" max_skill_level="1">
        <presets>
          <preset guid="940479898" is_toggle_slot="false">
            <default uid="0">
              <combo_state_default>
                <simple skill_id="WP_Item_FieldBoss_T3_DA_01" skill_id_disable="false" />
                <transition>
                  <use_skill skill_id="WP_Item_FieldBoss_T3_DA_01" next_combo_state="kComboStateDefault" />
                </transition>
              </combo_state_default>
            </default>
          </preset>
        </presets>
      </context>
      <trait_list />
    </skill_complex>
    <skill_complex guid="942773674" is_basic_attack="false" is_for_polymorphed_only="false" description="코완주키 단검 t3" unlock_level="1" id="SkillSet_WP_Item_FieldBoss_T3_DA_02" skill_enchant_category="kNone" skill_type="kPassiveSkill" feature_tag="BASE_LH" publisher_tag="ALL" skill_slot_affinity="kNotAssigned">
      <context uid="0" feature_tag="BASE_LH" publisher_tag="ALL" unlock_level="1" min_skill_level="1" max_skill_level="1">
        <presets>
          <preset guid="942708138" is_toggle_slot="false">
            <default uid="0">
              <combo_state_default>
                <simple skill_id="WP_Item_FieldBoss_T3_DA_02" skill_id_disable="false" />
                <transition>
                  <use_skill skill_id="WP_Item_FieldBoss_T3_DA_02" next_combo_state="kComboStateDefault" />
                </transition>
              </combo_state_default>
            </default>
          </preset>
        </presets>
      </context>
      <trait_list />
    </skill_complex>
  </skill_complex_list>
  <custom_list />
</hero_skill_set>